pypytorch/__init__.py
pypytorch/debug.py
pypytorch/tensor.py
pypytorch/tensortype.py
pypytorch/torchnode.py
pypytorch/utils.py
pypytorch/data/__init__.py
pypytorch/data/dataset.py
pypytorch/data/transform.py
pypytorch/functions/__init__.py
pypytorch/functions/function.py
pypytorch/functions/advanced/__init__.py
pypytorch/functions/advanced/activation.py
pypytorch/functions/advanced/avgpool.py
pypytorch/functions/advanced/batchnorm.py
pypytorch/functions/advanced/conv.py
pypytorch/functions/advanced/deconv.py
pypytorch/functions/advanced/dropout.py
pypytorch/functions/advanced/linear.py
pypytorch/functions/advanced/loss.py
pypytorch/functions/advanced/maxpool.py
pypytorch/functions/advanced/upsample.py
pypytorch/functions/basic/__init__.py
pypytorch/functions/basic/add.py
pypytorch/functions/basic/compare.py
pypytorch/functions/basic/concat.py
pypytorch/functions/basic/div.py
pypytorch/functions/basic/index.py
pypytorch/functions/basic/log.py
pypytorch/functions/basic/max.py
pypytorch/functions/basic/mean.py
pypytorch/functions/basic/min.py
pypytorch/functions/basic/mm.py
pypytorch/functions/basic/mul.py
pypytorch/functions/basic/neg.py
pypytorch/functions/basic/pow.py
pypytorch/functions/basic/sum.py
pypytorch/functions/basic/transpose.py
pypytorch/functions/basic/view.py
pypytorch/nn/__init__.py
pypytorch/nn/modules/__init__.py
pypytorch/nn/modules/activation.py
pypytorch/nn/modules/batchnorm.py
pypytorch/nn/modules/conv.py
pypytorch/nn/modules/deconv.py
pypytorch/nn/modules/dropout.py
pypytorch/nn/modules/linear.py
pypytorch/nn/modules/loss.py
pypytorch/nn/modules/module.py
pypytorch/nn/modules/pooling.py
pypytorch/nn/modules/upsample.py
pypytorch/optim/__init__.py
pypytorch/optim/adam.py
pypytorch/optim/optimizer.py
pypytorch/optim/sgd.py
test/__init__.py
test/test_module.py
pypytorch-0.0.1a0.dist-info/LICENSE
pypytorch-0.0.1a0.dist-info/METADATA
pypytorch-0.0.1a0.dist-info/WHEEL
pypytorch-0.0.1a0.dist-info/top_level.txt
pypytorch-0.0.1a0.dist-info/RECORD
